{
  "project_info": {
    "project_number": "153737717453",
    "firebase_url": "https://stuck-app-sm.firebaseio.com",
    "project_id": "stuck-app-sm",
    "storage_bucket": "stuck-app-sm.appspot.com"
  },
  "client": [
    {
      "client_info": {
        "mobilesdk_app_id": "1:153737717453:android:d76ed905c287370a",
        "android_client_info": {
          "package_name": "com.example.sammengistu.stuck"
        }
      },
      "oauth_client": [
        {
          "client_id": "153737717453-0jtudk4u1sjj6l8h1sghbrv6g18thqbf.apps.googleusercontent.com",
          "client_type": 3
        }
      ],
      "api_key": [
        {
          "current_key": "AIzaSyDTb_Q2qqiDDhc-bWVGhsn8Oydayb379MQ"
        }
      ],
      "services": {
        "analytics_service": {
          "status": 1
        },
        "appinvite_service": {
          "status": 1,
          "other_platform_oauth_client": []
        },
        "ads_service": {
          "status": 2
        }
      }
    }
  ],
  "configuration_version": "1"
}